vtracer-0.6.11.dist-info/METADATA
vtracer-0.6.11.dist-info/WHEEL
vtracer-0.6.11.dist-info/license_files/LICENSE-APACHE
vtracer-0.6.11.dist-info/license_files/LICENSE-MIT
vtracer/README.md
vtracer/vtracer.pyi
vtracer/__init__.py
vtracer/vtracer.cpython-311-aarch64-linux-gnu.so
vtracer-0.6.11.dist-info/RECORD
