Metadata-Version: 2.3
Name: vtracer
Version: 0.6.11
Classifier: Programming Language :: Rust
Classifier: Programming Language :: Python :: Implementation :: CPython
Classifier: Programming Language :: Python :: Implementation :: PyPy
License-File: LICENSE-APACHE
License-File: LICENSE-MIT
Summary: Python bindings for the Rust Vtracer raster-to-vector library
Keywords: svg,computer-graphics
Home-Page: http://www.visioncortex.org/vtracer
Author: Chris Tsang <chris.2y3@outlook.com>
Author-email: Chris Tsang <chris.2y3@outlook.com>
License: MIT
Requires-Python: >=3.7
Project-URL: Source Code, https://github.com/visioncortex/vtracer/
